telegra/__init__.py
telegra/core.py
telegra/drive.py
telegra/utils.py
telegra/__metadata__/DISCLAIMER.md
telegra/__metadata__/LICENSE
telegra/__metadata__/README.md
telegra/__metadata__/__init__.py
telegra/__metadata__/requirements.txt
telegra-0.0.3.dist-info/METADATA
telegra-0.0.3.dist-info/WHEEL
telegra-0.0.3.dist-info/top_level.txt
telegra-0.0.3.dist-info/RECORD
