Metadata-Version: 2.1
Name: telegra
Version: 0.0.3
Summary: A telegraph api and mirror.
Home-page: http://code.foxe6.kozow.com/telegra/
Author: f̣ộx̣ệ6
Author-email: foxe6@pm.me
License: AGPL-3.0
Project-URL: Sourcecode, http://code.foxe6.kozow.com/telegra.zip
Project-URL: Documentation, http://code.foxe6.kozow.com/telegra/docs/
Project-URL: Example, http://code.foxe6.kozow.com/telegra/test/
Project-URL: Funding, https://afdian.net/a/foxe6
Project-URL: Say Thanks!, https://saythanks.io/to/foxe6
Keywords: telegraph api open bypass great firewall mirror
Platform: UNKNOWN
Classifier: Programming Language :: Python :: 3.9
Classifier: Topic :: Utilities
Classifier: Natural Language :: English
Classifier: Intended Audience :: Developers
Classifier: License :: OSI Approved :: GNU Affero General Public License v3
Classifier: Operating System :: MacOS
Classifier: Operating System :: POSIX
Classifier: Operating System :: Microsoft :: Windows :: Windows 10
Classifier: Development Status :: 5 - Production/Stable
Requires-Python: >=3.5
Requires-Dist: cloudscraper (>=0.0.1)
Requires-Dist: requests (>=0.0.1)
Requires-Dist: threadwrapper (>=0.0.1)
Requires-Dist: omnitools (>=0.0.1)
Requires-Dist: lxml (>=0.0.1)
